alibabacloud_goodstech20191230/__init__.py
alibabacloud_goodstech20191230/client.py
alibabacloud_goodstech20191230/models.py
alibabacloud_goodstech20191230-2.0.2.dist-info/LICENSE
alibabacloud_goodstech20191230-2.0.2.dist-info/METADATA
alibabacloud_goodstech20191230-2.0.2.dist-info/WHEEL
alibabacloud_goodstech20191230-2.0.2.dist-info/top_level.txt
alibabacloud_goodstech20191230-2.0.2.dist-info/RECORD
